clicky/__init__.py
clicky/app.py
clicky/backends/__init__.py
clicky/backends/base.py
clicky/backends/discord.py
clicky/backends/slack.py
clicky/context.py
clicky/detect_run_string.py
clicky/frontends/__init__.py
clicky/frontends/click.py
clicky/logger.py
clicky/types.py
clicky-0.3.2.dist-info/LICENSE
clicky-0.3.2.dist-info/METADATA
clicky-0.3.2.dist-info/WHEEL
clicky-0.3.2.dist-info/RECORD
