Metadata-Version: 2.1
Name: clicky
Version: 0.3.2
Summary: Turn CLI applications into Slack & Discord bots.
Author: Tyler Kennedy
Author-email: tk@tkte.ch
Requires-Python: >=3.10,<4.0
Classifier: Programming Language :: Python :: 3
Classifier: Programming Language :: Python :: 3.10
Classifier: Programming Language :: Python :: 3.11
Classifier: Programming Language :: Python :: 3.12
Requires-Dist: typing-extensions (>=4.10)
